{
  "main": {
    "id": "06155fffeb6c2afa",
    "type": "split",
    "children": [
      {
        "id": "ebc4157edf88e5ba",
        "type": "tabs",
        "children": [
          {
            "id": "d44b9402589abbad",
            "type": "leaf",
            "state": {
              "type": "markdown",
              "state": {
                "file": "03-cla/c-cym01 cym introducción.md",
                "mode": "source",
                "source": false,
                "backlinks": false
              },
              "icon": "lucide-file",
              "title": "c-cym01 cym introducción"
            }
          }
        ]
      },
      {
        "id": "3df6130b7c25735a",
        "type": "tabs",
        "children": [
          {
            "id": "7a2dda2973348118",
            "type": "leaf",
            "state": {
              "type": "reveal-preview-view",
              "state": {},
              "icon": "lucide-file",
              "title": "Slide Preview"
            }
          }
        ]
      }
    ],
    "direction": "vertical"
  },
  "left": {
    "id": "b602c04a731b296c",
    "type": "split",
    "children": [
      {
        "id": "af95db91370f3ee0",
        "type": "tabs",
        "children": [
          {
            "id": "58a6bf3eeea06c75",
            "type": "leaf",
            "state": {
              "type": "file-explorer",
              "state": {
                "sortOrder": "alphabetical",
                "autoReveal": false
              },
              "icon": "lucide-folder-closed",
              "title": "Files"
            }
          },
          {
            "id": "9c932be67380cd5c",
            "type": "leaf",
            "state": {
              "type": "search",
              "state": {
                "query": "",
                "matchingCase": false,
                "explainSearch": false,
                "collapseAll": false,
                "extraContext": false,
                "sortOrder": "alphabetical"
              },
              "icon": "lucide-search",
              "title": "Search"
            }
          },
          {
            "id": "74b08449f93c0350",
            "type": "leaf",
            "state": {
              "type": "bookmarks",
              "state": {},
              "icon": "lucide-bookmark",
              "title": "Bookmarks"
            }
          }
        ]
      }
    ],
    "direction": "horizontal",
    "width": 322.5
  },
  "right": {
    "id": "f8c878636ee6998f",
    "type": "split",
    "children": [
      {
        "id": "aaca835876e592bb",
        "type": "tabs",
        "dimension": 45.46296296296296,
        "children": [
          {
            "id": "8c7ec6495dcddec6",
            "type": "leaf",
            "state": {
              "type": "outline",
              "state": {
                "file": "03-cla/c-cym01 cym introducción.md",
                "followCursor": false,
                "showSearch": false,
                "searchQuery": ""
              },
              "icon": "lucide-list",
              "title": "Outline of c-cym01 cym introducción"
            }
          },
          {
            "id": "144c44b7b3935a93",
            "type": "leaf",
            "state": {
              "type": "backlink",
              "state": {
                "file": "00-moc/obras MOC.md",
                "collapseAll": false,
                "extraContext": false,
                "sortOrder": "alphabetical",
                "showSearch": false,
                "searchQuery": "",
                "backlinkCollapsed": false,
                "unlinkedCollapsed": true
              },
              "icon": "links-coming-in",
              "title": "Backlinks for obras MOC"
            }
          },
          {
            "id": "e36f2709c75460b4",
            "type": "leaf",
            "state": {
              "type": "git-view",
              "state": {},
              "icon": "git-pull-request",
              "title": "Source Control"
            }
          },
          {
            "id": "dadcd00ddeddea13",
            "type": "leaf",
            "state": {
              "type": "git-history-view",
              "state": {},
              "icon": "history",
              "title": "History"
            }
          },
          {
            "id": "e8d2d76e9a26b86c",
            "type": "leaf",
            "state": {
              "type": "outgoing-link",
              "state": {
                "file": "03-cla/c-cym01 cym introducción.md",
                "linksCollapsed": false,
                "unlinkedCollapsed": true
              },
              "icon": "links-going-out",
              "title": "Outgoing links from c-cym01 cym introducción"
            }
          }
        ],
        "currentTab": 4
      },
      {
        "id": "b33cb9828f682814",
        "type": "tabs",
        "dimension": 18.51851851851852,
        "children": [
          {
            "id": "20c732dc2cc0ecaf",
            "type": "leaf",
            "state": {
              "type": "tag",
              "state": {
                "sortOrder": "frequency",
                "useHierarchy": false,
                "showSearch": false,
                "searchQuery": ""
              },
              "icon": "lucide-tags",
              "title": "Tags"
            }
          }
        ]
      },
      {
        "id": "0b21d0481a2a08a7",
        "type": "tabs",
        "dimension": 36.01851851851852,
        "children": [
          {
            "id": "d666d2187372564f",
            "type": "leaf",
            "state": {
              "type": "calendar",
              "state": {},
              "icon": "calendar-with-checkmark",
              "title": "Calendar"
            }
          }
        ]
      }
    ],
    "direction": "horizontal",
    "width": 236.5,
    "collapsed": true
  },
  "left-ribbon": {
    "hiddenItems": {
      "bases:Create new base": false,
      "switcher:Open quick switcher": false,
      "graph:Open graph view": false,
      "canvas:Create new canvas": false,
      "daily-notes:Open today's daily note": false,
      "templates:Insert template": false,
      "command-palette:Open command palette": false,
      "obsidian-git:Open Git source control": false,
      "obsidian-advanced-slides:Show Slide Preview": false,
      "notion-like-tables:Create loom": false,
      "obsidian-book-search-plugin:Create new book note": false,
      "obsidian-excalidraw-plugin:New drawing": false,
      "obsidian42-brat:BRAT": false,
      "callout-manager:Insert Callout": false,
      "digitalgarden:Digital Garden Publication Center": false,
      "obsidian-textgenerator-plugin:Generate Text!": false,
      "obsidian-textgenerator-plugin:Text Generator: Templates Packages Manager": false,
      "obsidian-markdown-formatting-assistant-plugin:Open Markdown Formatting Assistant": false,
      "local-media-embedder:Toggle media server": false
    }
  },
  "active": "d44b9402589abbad",
  "lastOpenFiles": [
    "03-cla/c-cym00-calendario.md",
    "03-cla/c-cym01 cym introducción.md",
    "05-obs/img/1_The Known Universe by AMNH 1.mp4",
    "05-obs/img/1_The Known Universe by AMNH.mp4",
    "04-tp/TP2025.md",
    "05-obs/tpl/cym-header.md",
    "03-cla/c-cym02-arte generativo.md",
    "04-tp/tp01-paradigmas operativos.md",
    "06-out/topoi/Energía.md",
    "06-out/topoi/energía/energía del gesto musical.md",
    "06-out/topoi/física/Física.md",
    "06-out/topoi/topoi BASE.base",
    "06-out/topoi/Forma Musical.md",
    "06-out/topoi/Sistemas de Universos.md",
    "06-out/topoi/Spectromorphology.md",
    "06-out/topoi/Vida artificial.md",
    "06-out/topoi/Virtualidad y realidad.md",
    "06-out/topoi/Sistemas complejos.md",
    "00-moc/topoi MOC.md",
    "06-out/topoi/Filosofías del Siglo XXI.md",
    "06-out/topoi/Humanos.md",
    "05-obs/tpl/t-topoi 1.md",
    "06-out/topoi/README.md",
    "06-out/topoi/Instalaciones.md",
    "06-out/topoi/Historia de la tecnología.md",
    "06-out/topoi/Intervencion del espacio público.md",
    "06-out/topoi/Augmented Cognition.md",
    "06-out/topoi/Aroma.md",
    "06-out/topoi/física",
    "06-out/operativos/inestabilidad de kelvin-helmholz/ref/Budiana et al._2020_The meshless numerical simulation of Kelvin–Helmholtz instability during the wave growth of liquid–l.pdf",
    "06-out/operativos/inestabilidad de kelvin-helmholz/ref/Goethe_1825_El juego de las nubes.epub",
    "06-out/operativos/inestabilidad de kelvin-helmholz/vendor/tthree-module-js.min.",
    "06-out/operativos/inestabilidad de kelvin-helmholz/ref/Olcina Cantos_2014_Enseñanzas climáticas en la obra de Kant.pdf",
    "06-out/operativos/inestabilidad de kelvin-helmholz/ref/Lacan_1963_Kant con Sade.pdf",
    "06-out/operativos/inestabilidad de kelvin-helmholz/vendor",
    "05-obs/img/eventos MOC-1755180996466.jpeg",
    "05-obs/img/eventos MOC-1755180996389.jpeg",
    "05-obs/img/eventos MOC-1755180996415.jpeg",
    "05-obs/img/eventos MOC-1755180996465.jpeg",
    "05-obs/img/eventos MOC-1755180996421.jpeg",
    "05-obs/img/eventos MOC-1755180996420.jpeg",
    "05-obs/img/eventos MOC-1755180996464.jpeg",
    "05-obs/img/eventos MOC-1755180996425.jpeg",
    "cym-metamap.canvas",
    "05-obs/img/Pasted image 20250618122453.png",
    "05-obs/img/Pasted image 20250529151452.png",
    "Sin título 1.canvas",
    "Sin título.canvas",
    "Untitled.canvas",
    "03-cla/cym-map.canvas"
  ]
}